qaws/__init__.py
qaws/qaws.py
qaws-0.4.1.dist-info/LICENSE
qaws-0.4.1.dist-info/METADATA
qaws-0.4.1.dist-info/WHEEL
qaws-0.4.1.dist-info/entry_points.txt
qaws-0.4.1.dist-info/top_level.txt
qaws-0.4.1.dist-info/RECORD
