Metadata-Version: 2.1
Name: qaws
Version: 0.4.1
Summary: Search AWS CloudWatch Logs with Insights queries, flexible time ranges and wildcards in log group names from your command line.
Home-page: https://github.com/kacirekj/saws
Author: Jiri Kacirek
Author-email: kacirek.j@gmail.com
License: UNKNOWN
Platform: UNKNOWN
Classifier: Programming Language :: Python :: 3
Classifier: License :: OSI Approved :: MIT License
Classifier: Operating System :: OS Independent
Requires-Python: >=3.6
Requires-Dist: boto3
